[
  {
    "question_id": "1",
    "answer": [
      "users",
      "postHistory",
      "posts"
    ]
  },
  {
    "question_id": "2",
    "answer": "NA"
  },
  {
    "question_id": "3",
    "answer": [
      "users.DisplayName",
      "posts.Tags",
      "posts.CommentCount"
    ]
  },
  {
    "question_id": "4",
    "answer": "NA"
  },
  {
    "question_id": "5",
    "answer": "NA"
  },
  {
    "question_id": "6",
    "answer": "NA"
  },
  {
    "question_id": "7",
    "answer": [
      "WHERE users.DisplayName = 'Mark Meckes'",
      "AND posts.CommentCount = 0"
    ]
  },
  {
    "question_id": "8",
    "answer": "NA"
  },
  {
    "question_id": "9",
    "answer": "NA"
  }
]